[
    [
        {
            "example": "어휘를 공부합니다. 단어를 외웁니다.",
            "selector": [
                "학습",
                "교육",
                "지식",
                "훈련"
            ],
            "answer": "학습",
            "eval_answer": "학습",
            "eval_explain": "\"어휘를 공부합니다. 단어를 외웁니다.\"라는 문장은 학습 활동을 설명하는 문장입니다. 따라서 '학습'이 가장 적절한 단어입니다. '교육'은 더 넓은 의미의 개념이고, '지식'은 결과물, '훈련'은 특정 기술을 익히는 과정에 더 가깝습니다.",
            "total_cost": 12.501
        },
        {
            "example": "이 방법은 쉽습니다. 다른 방법을 찾아보세요.",
            "selector": [
                "지시",
                "규제",
                "명령",
                "통제"
            ],
            "answer": "지시",
            "eval_answer": "지시  ",
            "eval_explain": "문맥상 \"이 방법은 쉽습니다. 다른 방법을 찾아보세요.\"라는 문장은 어떤 방법을 제시하거나 권장하는 의미를 담고 있습니다. 따라서 '지시'가 가장 적합한 단어입니다. '규제', '명령', '통제'는 모두 강제적이거나 제한적인 의미를 포함하고 있어 문맥에 맞지 않습니다.",
            "total_cost": 12.609000000000002
        },
        {
            "example": "억 소리가 났다.억울한 표정을 지었다.",
            "selector": [
                "슬픔",
                "감정",
                "기분",
                "사랑"
            ],
            "answer": "감정",
            "eval_answer": "감정",
            "eval_explain": "'억 소리가 났다'와 '억울한 표정을 지었다'는 모두 '감정'과 관련된 표현이다. '슬픔', '기분', '사랑'은 문맥에 맞지 않는다.",
            "total_cost": 12.096
        }
    ],
    [
        {
            "example": "빛이 방을 밝힙니다. (   )이 빛을 줍니다.",
            "selector": [
                "일광",
                "햇빛",
                "태양",
                "해"
            ],
            "answer": "태양",
            "eval_answer": "태양",
            "eval_explain": "빛이 방을 밝힙니다. 태양이 빛을 줍니다.",
            "total_cost": 6.21
        },
        {
            "example": "(   )가 울리고 있어요.   새로운 전화기를 샀어요.",
            "selector": [
                "스마트폰",
                "핸드폰",
                "휴대전화",
                "전화기"
            ],
            "answer": "전화기",
            "eval_answer": "전화기",
            "eval_explain": "전화기가 울리고 있어요.   새로운 전화기를 샀어요.",
            "total_cost": 6.399000000000001
        }
    ],
    [
        {
            "example": "잠이 (   ).   잠을 푹 자세요.",
            "selector": [
                "결핍됩니다",
                "부족합니다",
                "불충분합니다",
                "모자랍니다"
            ],
            "answer": "부족합니다",
            "eval_answer": "부족합니다",
            "eval_explain": "잠이 부족합니다.   잠을 푹 자세요.",
            "total_cost": 6.587999999999999
        },
        {
            "example": "냉장고가 고장 (   ). 음식을 꺼내 먹었어요.",
            "selector": [
                "생겼어요",
                "일어났어요",
                "발생했어요",
                "났어요"
            ],
            "answer": "났어요",
            "eval_answer": "났어요",
            "eval_explain": "냉장고가 고장 났어요. 음식을 꺼내 먹었어요.",
            "total_cost": 6.75
        }
    ],
    [
        {
            "example": "집(   ) 아주 큽니다. 정원이 아름답습니다.",
            "selector": [
                "가",
                "이",
                "은",
                "는"
            ],
            "answer": "이",
            "eval_answer": "이",
            "eval_explain": "집이 아주 큽니다. 정원이 아름답습니다.",
            "total_cost": 5.7509999999999994
        },
        {
            "example": "신호등이 빨간불입니(   ). 차들이 멈춰 섭니다.",
            "selector": [
                "뿐",
                "까지",
                "만",
                "다"
            ],
            "answer": "다",
            "eval_answer": "다",
            "eval_explain": "신호등이 빨간불입니다. 차들이 멈춰 섭니다.",
            "total_cost": 6.021
        }
    ],
    [
        {
            "example": "https://topikkorea.s3.amazonaws.com/topik_image/3b47010c-23ef-11ef-8928-e5a43cd400fd.png",
            "selector": [
                "틀린 내용: 행복 요리 교실은 매주 일요일 오전 10시에 열립니다.",
                "엄마, 아빠 그리고 아이가 함께하는 행복 요리 교실에서 맛있는 불고기를 만들어보세요.",
                "토요일 오전 10시에 열리는 불고기 요리 교실에서 가족과 함께 신나고 유익한 시간을 가져보세요.",
                "매주 토요일 아침 10시, 행복 요리 학원에서 가족과 함께하는 불고기 요리 교실에 참여하세요!"
            ],
            "answer": "틀린 내용: 행복 요리 교실은 매주 일요일 오전 10시에 열립니다.",
            "eval_answer": "틀린 내용: 행복 요리 교실은 매주 일요일 오전 10시에 열립니다.",
            "explain": "",
            "total_cost": 18.63
        },
        {
            "example": "https://topikkorea.s3.amazonaws.com/topik_image/3b2b9671-23ef-11ef-9ac0-e5a43cd400fd.png",
            "selector": [
                "토요일에는 미영 씨와 함께 등산을 갑니다.",
                "틀린 내용: 수요일에 민수 씨를 만납니다.",
                "월요일과 목요일에는 수영이 있습니다.",
                "수요일에는 쇼핑을 할 계획입니다."
            ],
            "answer": "틀린 내용: 수요일에 민수 씨를 만납니다.",
            "eval_answer": "틀린 내용: 수요일에 민수 씨를 만납니다.",
            "explain": "",
            "total_cost": 12.771
        },
        {
            "example": "https://topikkorea.s3.amazonaws.com/topik_image/31e8b2ea-23ef-11ef-a3f7-e5a43cd400fd.png",
            "selector": [
                "틀린 내용: 이 모임은 토요일에 열립니다.",
                "금요일 오후에 우리와 함께 노래해요.",
                "한국 친구들과 함께 노래를 즐길 수 있어요.",
                "한국 노래를 배우러 3층 309호 교실로 오세요."
            ],
            "answer": "틀린 내용: 이 모임은 토요일에 열립니다.",
            "eval_answer": "틀린 내용: 이 모임은 토요일에 열립니다.",
            "explain": "",
            "total_cost": 12.068999999999999
        }
    ],
    [
        {
            "example": "나는 언제나 희망을 잃지 않고 미래를 향해 나아갈 것이다.",
            "selector": [
                "나는 미래에 대한 두려움 때문에 움츠러들어 있다.",
                "나는 미래에 대한 불안을 느끼지 않는다.",
                "나는 미래를 향해 나아가는 것을 포기했다",
                "나는 항상 우울하고 포기하는 편이다."
            ],
            "answer": "나는 미래를 향해 나아가는 것을 포기했다",
            "eval_answer": "나는 미래를 향해 나아가는 것을 포기했다",
            "explain": "",
            "total_cost": 2.538
        },
        {
            "example": "어제 일을 하다가 큰 실수를 저질렀어요. 그래서 상사에게 사과를 하고, 다시 신중하게 일을 처리하려고 노력했어요.",
            "selector": [
                "더 많은 실수를 저질렀다.",
                "어제 일을 하다가 큰 실수를 저질렀어요. 그래서 상사에게 사과를 하고, 다시 신중하게 일을 처리하려고 노력했어요",
                "상사에게 사과했더니 칭찬을 받았다.",
                "실수를 한 것을 숨겼다."
            ],
            "answer": "어제 일을 하다가 큰 실수를 저질렀어요. 그래서 상사에게 사과를 하고, 다시 신중하게 일을 처리하려고 노력했어요",
            "eval_answer": "어제 일을 하다가 큰 실수를 저질렀어요. 그래서 상사에게 사과를 하고, 다시 신중하게 일을 처리하려고 노력했어요",
            "explain": "",
            "total_cost": 2.8755
        },
        {
            "example": "저는 매일 아침 지하철을 타고 출근합니다. 지하철 안에서는 책을 읽거나 음악을 들으면서 시간을 보내곤 해요. 가끔은 친구들과 만나기 위해 지하철을 타고 이동하기도 하는데, 그럴 때는 항상 설레는 기분이 들어요. 지하철은 저에게 편리하고 소중한 교통수단입니다.",
            "selector": [
                "가끔은 친구들과 만나기 위해 비행기를 타고 이동하기도 합니다.",
                "저는 매일 아침 자전거를 타고 출근합니다.",
                "버스를 타고 출근하는 것이 더 빠르고 편리하다고 생각합니다",
                "지하철 안에서는 요가를 하거나 체조를 하는 것을 즐깁니다."
            ],
            "answer": "버스를 타고 출근하는 것이 더 빠르고 편리하다고 생각합니다",
            "eval_answer": "버스를 타고 출근하는 것이 더 빠르고 편리하다고 생각합니다",
            "explain": "",
            "total_cost": 4.131
        }
    ],
    [
        {
            "example": "크기가 작을수록 더 많은 선택지가 생기는 것 같아요. 작은 크기의 물건들은 휴대하기도 편리하고 수납하기도 쉬워요. 하지만 때로는 큰 크기의 물건이 더 효율적일 때도 있죠. 크기는 상황에 따라 다르게 중요하게 작용할 수 있어요.",
            "selector": [
                "작은 크기의 물건은 휴대하기도 편리하고 수납하기도 쉽습니다.",
                "작은 크기의 물건은 항상 효율적입니다.",
                "크기가 작을수록 선택지가 제한될 수 있습니다.",
                "큰 크기의 물건이 항상 더 좋습니다."
            ],
            "answer": "작은 크기의 물건은 휴대하기도 편리하고 수납하기도 쉽습니다.",
            "eval_answer": "작은 크기의 물건은 휴대하기도 편리하고 수납하기도 쉽습니다.",
            "explain": "주어진 예시에서는 작은 크기의 물건이 휴대와 수납에 편리하다는 점을 강조하고 있습니다. 또한, 크기는 상황에 따라 다르게 중요하게 작용할 수 있다고 언급하고 있습니다. 따라서, 작은 크기의 물건이 항상 효율적이거나 큰 크기의 물건이 항상 더 좋다는 내용은 맞지 않습니다. 크기가 작을수록 선택지가 제한된다는 내용도 예시와 일치하지 않습니다.",
            "total_cost": 12.892499999999998
        },
        {
            "example": "요즘 스트레스가 너무 많이 쌓여서 힘들어요. 매일 일어나면 머리가 아파요. 운동을 해도 마음이 편해지지 않아요. 이번 주말에는 친구들과 함께 여행을 가서 스트레스를 풀어야겠어요.",
            "selector": [
                "저는 매일 운동을 합니다.",
                "저는 친구들과 함께 여행을 가기로 했습니다.",
                "저는 요즘 매일 머리가 아픕니다.",
                "저는 스트레스를 풀기 위해 여행을 가기로 했습니다."
            ],
            "answer": "저는 스트레스를 풀기 위해 여행을 가기로 했습니다.",
            "eval_answer": "저는 스트레스를 풀기 위해 여행을 가기로 했습니다.",
            "explain": "주어진 예문에서 화자는 스트레스를 많이 받고 있으며, 이를 해소하기 위해 친구들과 함께 여행을 가기로 했다고 말하고 있습니다. 따라서 중심 내용은 스트레스를 풀기 위해 여행을 가기로 한 것입니다.",
            "total_cost": 9.693
        },
        {
            "example": "그는 매일 아침 일하기 싫어하는 마음을 이기고 회사로 향한다. 일하기 싫은 날이라도 열심히 일해야 한다는 생각에 자신을 다독이며 일상을 이어간다.",
            "selector": [
                "그는 매일 아침 일어나기 싫어하는 마음을 이기고 회사로 출근한다.",
                "그는 매일 아침 늦게 일어나서 회사에 늦게 도착한다.",
                "그는 매일 아침 일어나는 것을 즐긴다.",
                "그는 매일 아침 일어나는 것을 귀찮아한다."
            ],
            "answer": "그는 매일 아침 일어나기 싫어하는 마음을 이기고 회사로 출근한다.",
            "eval_answer": "그는 매일 아침 일어나기 싫어하는 마음을 이기고 회사로 출근한다.",
            "explain": "주어진 예문에서 그는 매일 아침 일하기 싫어하는 마음을 이기고 회사로 향한다고 언급되어 있다. 이는 선택지 1번의 내용과 일치한다. 나머지 선택지들은 예문의 내용과 맞지 않다.",
            "total_cost": 10.719000000000001
        }
    ],
    [
        {
            "example": "운동은 건강에 좋다고 하지만 나는 항상 귀찮아서 자꾸 미루게 된다. 그래서 요즘은 친구와 함께 운동을 시작했는데, 함께 하니까 더 재미있고 즐겁다. 매일 조금씩이라도 운동을 하면서 몸도 ( ㉠ ) 기분도 좋아진다. 앞으로는 꾸준히 운동을 해서 건강한 삶을 살고 싶다.",
            "questions": [
                {
                    "question": "( ㉠ )에 들어갈 말로 가장 알맞은 것을 고르십시오.",
                    "selector": [
                        "건강해지고",
                        "무거워지고",
                        "나빠지고",
                        "아파지고"
                    ],
                    "answer": "건강해지고",
                    "eval_answer": "건강해지고",
                    "eval_explain": "문맥상 운동을 하면서 몸이 건강해지고 기분도 좋아진다는 긍정적인 변화가 나타나야 하므로 '건강해지고'가 가장 적절하다."
                },
                {
                    "question": "<보기>의 내용과 맞는 것을 고르십시오.",
                    "selector": [
                        "나는 운동을 혼자 하는 것이 더 재미있다.",
                        "나는 운동을 시작한 후로 기분이 나빠졌다.",
                        "나는 친구와 함께 운동을 시작했다.",
                        "나는 운동을 미루지 않고 항상 열심히 한다."
                    ],
                    "answer": "나는 친구와 함께 운동을 시작했다.",
                    "eval_answer": "나는 친구와 함께 운동을 시작했다.",
                    "eval_explain": "주어진 예문에서 \"요즘은 친구와 함께 운동을 시작했는데\"라는 문장이 있으므로, 이 문장을 올바르게 서술한 선택지는 3번이다."
                }
            ],
            "total_cost": 23.490000000000002
        },
        {
            "example": "제가 새로운 프로젝트를 시작하기 전에 팀장님의 허락을 받아야 합니다. 그래서 어제 오후에 팀장님께 면담을 요청했고, 내 아이디어를 설명했습니다. 팀장님은 내 제안을 듣고 고민한 뒤에 허락을 해 주셨습니다. 이제부터는 프로젝트를 진행( ㉠ ) 수 있게 되었습니다.",
            "questions": [
                {
                    "question": "( ㉠ )에 들어갈 말로 가장 알맞은 것을 고르십시오.",
                    "selector": [
                        "할 ",
                        "못할 ",
                        "하지 않을 ",
                        "중단할 "
                    ],
                    "answer": "할",
                    "eval_answer": "할",
                    "eval_explain": "문맥상 프로젝트를 진행할 수 있게 되었다는 긍정적인 의미가 필요합니다. 따라서 \"할\"이 적절합니다."
                },
                {
                    "question": "<보기>의 내용과 맞는 것을 고르십시오.",
                    "selector": [
                        "저는 팀장님의 허락 없이 프로젝트를 시작했습니다.",
                        "저는 팀장님께 면담을 요청하여 아이디어를 설명했습니다.",
                        "팀장님은 제 제안을 듣고 바로 거절하셨습니다.",
                        "저는 프로젝트를 진행할 수 없게 되었습니다."
                    ],
                    "answer": "저는 팀장님께 면담을 요청하여 아이디어를 설명했습니다.",
                    "eval_answer": "저는 팀장님께 면담을 요청하여 아이디어를 설명했습니다.",
                    "eval_explain": "이 문장은 주어진 예시와 일치하며, 팀장님께 면담을 요청하고 아이디어를 설명한 내용을 정확히 반영하고 있습니다."
                }
            ],
            "total_cost": 24.111
        },
        {
            "example": "한국 음식 중에서 김치는 굉장히 인기 있는 반찬이다. 김치는 배추와 양념 재료를 사용하여 발효시켜 만든다. 매운 맛을 좋아하는 사람들은 고추장을 더 넣어 매콤하게 만들기도 한다. 김치는 소화에도 도움이 되고 영양가도 높아 건강에 좋다. 요즘에는 다양한 종류의 김치도 ( ㉠ ) 많은 사람들이 즐긴다.",
            "questions": [
                {
                    "question": "( ㉠ )에 들어갈 말로 가장 알맞은 것을 고르십시오.",
                    "selector": [
                        "만들어져서",
                        "팔려서",
                        "버려져서",
                        "먹지 않아서"
                    ],
                    "answer": "만들어져서",
                    "eval_answer": "만들어져서",
                    "eval_explain": "문맥상 다양한 종류의 김치가 만들어져서 많은 사람들이 즐긴다는 의미가 가장 자연스럽다."
                },
                {
                    "question": "<보기>의 내용과 맞는 것을 고르십시오.",
                    "selector": [
                        "김치는 배추와 양념 재료를 사용하여 발효시켜 만든다.",
                        "김치는 매운 맛을 좋아하는 사람들에게 인기가 없다.",
                        "김치는 소화에 도움이 되지 않는다.",
                        "요즘에는 김치를 먹는 사람이 줄어들고 있다."
                    ],
                    "answer": "김치는 배추와 양념 재료를 사용하여 발효시켜 만든다.",
                    "eval_answer": "김치는 배추와 양념 재료를 사용하여 발효시켜 만든다.",
                    "eval_explain": "주어진 예문에서 김치의 제조 방법을 설명한 문장으로, 올바르게 서술된 문장이다."
                }
            ],
            "total_cost": 25.0155
        },
        {
            "example": "사람들은 다양한 색깔을 좋아합니다. ( ㉠ ) 색깔의 옷을 입으면 기분이 좋아지기도 합니다. 집안을 꾸밀 때도 각 방마다 다른 색깔을 고려해야 합니다. 심리학에 따르면 색깔은 감정과 연관이 깊다고 합니다. 빨간색은 열정을 상징하고 파란색은 평화를 상징한다고 합니다.",
            "questions": [
                {
                    "question": "( ㉠ )에 들어갈 말로 가장 알맞은 것을 고르십시오.",
                    "selector": [
                        "어두운",
                        "예쁜",
                        "무채색",
                        "투명한"
                    ],
                    "answer": "예쁜",
                    "eval_answer": "예쁜",
                    "eval_explain": "문맥상 기분이 좋아지는 색깔을 언급하고 있으므로 '예쁜' 색깔이 적절합니다."
                },
                {
                    "question": "<보기>의 내용과 맞는 것을 고르십시오.",
                    "selector": [
                        "빨간색은 평화를 상징합니다.",
                        "파란색은 열정을 상징합니다.",
                        "색깔은 감정과 연관이 없습니다.",
                        "심리학에 따르면 색깔은 감정과 연관이 깊습니다."
                    ],
                    "answer": "심리학에 따르면 색깔은 감정과 연관이 깊습니다.",
                    "eval_answer": "심리학에 따르면 색깔은 감정과 연관이 깊습니다.",
                    "eval_explain": "본문에서 \"심리학에 따르면 색깔은 감정과 연관이 깊다고 합니다.\"라는 문장이 있으므로, 이 선택지가 올바릅니다."
                }
            ],
            "total_cost": 24.313499999999998
        }
    ],
    [
        {
            "example": "(라) 기도를 통해 내게 힘을 주시는 하나님께 감사를 표현합니다. (가) 매일 아침 기도를 드리는 것은 저의 습관입니다. (다) 어려운 시기에는 더욱 깊은 기도가 필요하다고 느낍니다. (나) 기도는 믿음을 표현하는 소중한 시간입니다. ",
            "selector": [
                "(가) - (나) - (라) - (다)",
                "(가) - (나) - (다) - (라)",
                "(나) - (가) - (라) - (다)",
                "(나) - (라) - (가) - (다)"
            ],
            "answer": "(나) - (가) - (라) - (다)",
            "eval_answer": "(나) - (가) - (라) - (다)",
            "eval_explain": "",
            "total_cost": 2.2275
        },
        {
            "example": "(가) 오늘 저녁에 방송되는 첫 회를 놓치지 않고 시청해야겠어요. (다) 방송을 통해 새로운 드라마 소식을 접했습니다. (나) 드라마 속 이야기가 너무 궁금해서 기대가 되네요. (라) 그 드라마는 내가 좋아하는 배우가 주연으로 출연한다고 합니다. ",
            "selector": [
                "(다) - (라) - (가) - (나)",
                "(다) - (가) - (라) - (나)",
                "(다) - (나) - (라) - (가)",
                "(가) - (다) - (나) - (라)"
            ],
            "answer": "(다) - (라) - (가) - (나)",
            "eval_answer": "(다) - (라) - (가) - (나)",
            "eval_explain": "",
            "total_cost": 2.2275
        }
    ],
    [
        {
            "example": "https://topikkorea.s3.amazonaws.com/topik_image/6b02a020-23ef-11ef-86a8-e5a43cd400fd.png",
            "questions": [
                {
                    "question": "이 글을 쓴 의도와 가장 가까운 것을 고르십시오.",
                    "selector": [
                        "주문 방법을 물어보려고",
                        "구두를 더 주문하고 싶어서",
                        "구두 사이즈를 바꾸고 싶어서",
                        "구두를 산 날짜를 확인하려고"
                    ],
                    "answer": "구두 사이즈를 바꾸고 싶어서",
                    "eval_answer": "구두 사이즈를 바꾸고 싶어서",
                    "eval_explain": ""
                },
                {
                    "question": "이 글의 내용과 같은 것을 고르십시오.",
                    "selector": [
                        "지난주에 구두를 받았습니다.",
                        "인터넷으로 구두를 샀습니다.",
                        "240 사이즈의 구두를 샀습니다.",
                        "쇼핑몰에 이메일을 여러 번 보냈습니다."
                    ],
                    "answer": "인터넷으로 구두를 샀습니다.",
                    "eval_answer": "인터넷으로 구두를 샀습니다.",
                    "eval_explain": ""
                }
            ],
            "total_cost": 0
        }
    ],
    [
        {
            "example": "태양은 지구 주변을 공전하며 빛과 열을 우리에게 제공합니다. (㉠) 태양빛은 식물이 광합성을 통해 산소를 생산하고 생물들이 에너지를 얻는 데 중요한 역할을 합니다. (㉡) 태양은 우리의 에너지원이기도 한데, 태양열 발전을 통해 전기를 생산할 수 있습니다. (㉢) 태양은 우주에서 가장 크고 중요한 별 중 하나로, 우리의 생활과 자연에 미치는 영향은 매우 큽니다. (㉣) 태양은 우리의 삶에 빛과 에너지를 주는 존재로, 우리는 항상 그 존재를 감사히 여겨야 합니다.",
            "questions": [
                {
                    "question": "다음 문장이 들어갈 곳으로 가장 알맞은 것을 고르십시오.",
                    "example": " 태양은 매일 뜨고 지는데, 이를 통해 낮과 밤이 생기며 계절이 변화합니다.",
                    "selector": [
                        "㉠",
                        "㉡",
                        "㉢",
                        "㉣"
                    ],
                    "answer": "㉣",
                    "eval_answer": "㉣",
                    "eval_explain": ""
                },
                {
                    "question": "윗글의 내용과 같은 것을 고르십시오.",
                    "selector": [
                        "태양은 지구 주변을 공전하며 빛과 열을 제공합니다.",
                        "태양은 매일 뜨고 지며 계절이 변하지 않습니다.",
                        "태양빛은 식물이 광합성을 통해 물을 생산합니다.",
                        "태양은 우리의 에너지원이 아니며 전기를 생산할 수 없습니다."
                    ],
                    "answer": "태양은 지구 주변을 공전하며 빛과 열을 제공합니다.",
                    "eval_answer": "태양은 지구 주변을 공전하며 빛과 열을 제공합니다.",
                    "eval_explain": "태양은 지구 주변을 공전하지 않고, 지구가 태양 주변을 공전합니다. 하지만 선택지 중에서 가장 올바른 서술은 1번입니다. 나머지 선택지들은 명백히 틀린 정보를 포함하고 있습니다. 2번은 계절이 변하지 않는다고 잘못 서술했고, 3번은 광합성의 결과로 물이 아닌 산소가 생산된다고 잘못 서술했으며, 4번은 태양이 에너지원이 아니며 전기를 생산할 수 없다고 잘못 서술했습니다."
                }
            ],
            "total_cost": 27.9045
        }
    ],
    [
        {
            "example": "가수는 음악을 통해 감정을 전달하고 사람들의 마음을 움직이는 예술가입니다. 노래를 통해 자신의 이야기나 세상을 담아내어 팬들과 소통합니다. 가수들은 무대 위에서 노래하며 사람들에게 희망과 ( ㉠ ). 또한, 가수들은 자신의 음악적 재능과 노력으로 성공을 거두는 경우도 많습니다. 가수로서의 인기와 영향력은 그들이 가진 음악적 능력과 카리스마에서 비롯됩니다. 종종 가수들은 팬들과의 소통을 위해 공연이나 팬미팅을 통해 특별한 순간을 만들기도 합니다.",
            "questions": [
                {
                    "question": "㉠ 에 들어갈 알맞은 말을 고르십시오.",
                    "selector": [
                        "용기를 줍니다",
                        "슬픔을 줍니다",
                        "두려움을 줍니다",
                        "혼란을 줍니다"
                    ],
                    "answer": "용기를 줍니다",
                    "eval_answer": "용기를 줍니다",
                    "eval_explain": "가수는 음악을 통해 사람들에게 긍정적인 감정을 전달하는 예술가입니다. 따라서 \"희망과 용기를 줍니다\"가 가장 적절한 표현입니다."
                },
                {
                    "question": "이 글의 내용과 같은 것을 고르십시오.",
                    "selector": [
                        "가수는 음악을 통해 사람들에게 두려움을 줍니다.",
                        "가수들은 무대 위에서 노래하며 사람들에게 슬픔을 줍니다.",
                        "가수들은 팬들과의 소통을 위해 공연이나 팬미팅을 통해 특별한 순간을 만듭니다.",
                        "가수로서의 인기와 영향력은 그들이 가진 두려움에서 비롯됩니다."
                    ],
                    "answer": "가수들은 팬들과의 소통을 위해 공연이나 팬미팅을 통해 특별한 순간을 만듭니다.",
                    "eval_answer": "가수들은 팬들과의 소통을 위해 공연이나 팬미팅을 통해 특별한 순간을 만듭니다.",
                    "eval_explain": "이 문장은 가수들이 팬들과 소통하기 위해 공연이나 팬미팅을 통해 특별한 순간을 만든다는 내용을 정확하게 서술하고 있습니다."
                }
            ],
            "total_cost": 29.4435
        },
        {
            "example": "사고를 당했을 때는 냉정하게 대처하는 것이 중요합니다. 사고 후에는 상대방과의 원만한 해결을 위해 서로 양보하는 자세가 필요합니다. 사고가 나면 주변 시선이 부담스러울 수 있지만, 빠르게 대처하는 것이 더 큰 문제를 예방할 ( ㉠ ). 사고로 인한 상처는 시간이 지나면 치유되지만, 예방을 통해 미리 대비하는 습관이 중요합니다. 사고가 나면 주변 지인들의 도움을 받는 것도 큰 힘이 될 수 있습니다. 사고 후에는 반드시 보험처리를 해야 하며, 이를 통해 추가적인 손해를 방지할 수 있습니다.",
            "questions": [
                {
                    "question": "㉠ 에 들어갈 알맞은 말을 고르십시오.",
                    "selector": [
                        "데 도움이 될 수 있습니다",
                        "데 불편할 수 있습니다",
                        "데 무의미할 수 있습니다",
                        "데 방해가 될 수 있습니다"
                    ],
                    "answer": "데 도움이 될 수 있습니다",
                    "eval_answer": "데 도움이 될 수 있습니다",
                    "eval_explain": "문맥상 사고가 났을 때 빠르게 대처하는 것이 더 큰 문제를 예방하는 데 도움이 된다는 의미가 가장 적절합니다."
                },
                {
                    "question": "이 글의 내용과 같은 것을 고르십시오.",
                    "selector": [
                        "사고를 당했을 때는 당황하지 않고 냉정하게 대처하는 것이 중요합니다.",
                        "사고 후에는 상대방과의 원만한 해결을 위해 서로 양보하는 자세가 필요하지 않습니다.",
                        "사고가 나면 주변 시선이 부담스러워서 대처하지 않는 것이 좋습니다.",
                        "사고로 인한 상처는 시간이 지나도 치유되지 않습니다."
                    ],
                    "answer": "사고를 당했을 때는 당황하지 않고 냉정하게 대처하는 것이 중요합니다.",
                    "eval_answer": "사고를 당했을 때는 당황하지 않고 냉정하게 대처하는 것이 중요합니다.",
                    "eval_explain": "사고를 당했을 때 냉정하게 대처하는 것이 중요하다는 내용이 문맥에 맞고, 다른 선택지들은 문맥에 맞지 않거나 부정확한 내용을 담고 있습니다."
                }
            ],
            "total_cost": 34.2225
        },
        {
            "example": "세탁소에서 옷을 세탁하러 가는 것이 귀찮았지만, 최근에 옷이 너무 많아져서 어쩔 수 없이 다녀야 했습니다. 세탁소 아저씨는 항상 밝은 미소로 옷을 반겨주셔서 기분이 좋았습니다. 옷을 찾으러 가는 날이면 기분이 좋아서 ( ㉠ ) 되었습니다. 세탁소에서 옷을 찾을 때마다 새로운 옷을 사야겠다는 생각이 들 정도로 깨끗하고 정갈하게 접어져 있는 모습이 마음에 들었습니다. 세탁소에서 옷을 찾아가는 시간이 마치 작은 힐링 타임이 되어버렸습니다.",
            "questions": [
                {
                    "question": "㉠ 에 들어갈 알맞은 말을 고르십시오.",
                    "selector": [
                        "세탁소 아저씨와 대화를 나누게",
                        "새로운 옷을 사러 가게",
                        "기분이 나빠지게",
                        "세탁소를 피하게"
                    ],
                    "answer": "세탁소 아저씨와 대화를 나누게",
                    "eval_answer": "세탁소 아저씨와 대화를 나누게",
                    "eval_explain": "문맥상 세탁소 아저씨가 밝은 미소로 옷을 반겨주셔서 기분이 좋아진다는 내용이므로, 옷을 찾으러 가는 날 기분이 좋아져서 세탁소 아저씨와 대화를 나누게 된다는 것이 자연스럽습니다."
                },
                {
                    "question": "이 글의 내용과 같은 것을 고르십시오.",
                    "selector": [
                        "세탁소 아저씨는 항상 무표정으로 옷을 반겨주십니다.",
                        "세탁소에서 옷을 찾는 시간이 힐링 타임이 되었습니다.",
                        "옷을 찾으러 가는 날이면 기분이 나빠집니다.",
                        "세탁소에서 옷을 찾을 때마다 실망하게 됩니다."
                    ],
                    "answer": "세탁소에서 옷을 찾는 시간이 힐링 타임이 되었습니다.",
                    "eval_answer": "세탁소에서 옷을 찾는 시간이 힐링 타임이 되었습니다.",
                    "eval_explain": "본문에서 세탁소에서 옷을 찾아가는 시간이 작은 힐링 타임이 되었다고 언급하고 있으므로, 이 선택지가 올바른 서술입니다."
                }
            ],
            "total_cost": 35.153999999999996
        },
        {
            "example": "신발은 일상생활에서 필수품 중 하나로, 보호와 편의를 제공합니다. 다양한 디자인과 스타일의 신발이 있어, 각자의 취향에 맞게 선택할 ( ㉠ ). 옷과 신발의 조합은 전체 패션을 완성하는 중요한 부분이며, 신발 하나로 스타일을 한껏 뽐낼 수 있습니다. 신발을 신고 다니면서 걸음걸이도 변화되어, 자신감을 얻을 수 있습니다. 또한, 편안한 신발을 신으면 하루 종일 피로를 덜 느끼게 됩니다. 따라서, 신발은 우리 삶에 큰 영향을 미치는 중요한 아이템입니다.",
            "questions": [
                {
                    "question": "㉠ 에 들어갈 알맞은 말을 고르십시오.",
                    "selector": [
                        "기회를 제공합니다.",
                        "방법을 모색합니다.",
                        "이유를 설명합니다.",
                        "문제를 해결합니다."
                    ],
                    "answer": "기회를 제공합니다.",
                    "eval_answer": "기회를 제공합니다.",
                    "eval_explain": "문맥상 다양한 디자인과 스타일의 신발이 있어 각자의 취향에 맞게 선택할 \"기회를 제공합니다\"가 가장 자연스럽습니다."
                },
                {
                    "question": "이 글의 내용과 같은 것을 고르십시오.",
                    "selector": [
                        "신발은 일상생활에서 필수품이 아니며, 보호와 편의를 제공하지 않습니다.",
                        "다양한 디자인과 스타일의 신발이 없어, 선택의 폭이 좁습니다.",
                        "옷과 신발의 조합은 전체 패션을 완성하는 중요한 부분입니다.",
                        "신발을 신고 다니면서 걸음걸이가 변화되지 않습니다."
                    ],
                    "answer": "옷과 신발의 조합은 전체 패션을 완성하는 중요한 부분입니다.",
                    "eval_answer": "옷과 신발의 조합은 전체 패션을 완성하는 중요한 부분입니다.",
                    "eval_explain": "주어진 예시에서 옷과 신발의 조합이 전체 패션을 완성하는 중요한 부분이라고 명시되어 있으므로, 이 선택지가 올바릅니다."
                }
            ],
            "total_cost": 30.9285
        }
    ]
]